omi_async_http_client/__init__.py
omi_async_http_client/_exceptions.py
omi_async_http_client/_model.py
omi_async_http_client/_status_code.py
omi_async_http_client/aiohttp_backend.py
omi_async_http_client/async_http_client.py
omi_async_http_client/fastapi_testclient_backend.py
omi_async_http_client/httpx_backend.py
omi_async_http_client/requests_backend.py
omi_async_http_client-0.2.2.dist-info/METADATA
omi_async_http_client-0.2.2.dist-info/WHEEL
omi_async_http_client-0.2.2.dist-info/top_level.txt
omi_async_http_client-0.2.2.dist-info/RECORD
