Metadata-Version: 2.1
Name: omi-async-http-client
Version: 0.2.2
Summary: An async http client implemented with [asyncio] and backends
Home-page: https://github.com/limccn/omi_async_http_client
Author: limccn
Author-email: limccn@me.com
License: Apache License 2.1
Keywords: http_client,aio,async,asyncio
Platform: any
Requires-Dist: pydantic
